{
    "2036": {
        "notes": []
    },
    "4406": {
        "notes": []
    },
    "2384": {
        "notes": []
    },
    "4453": {
        "notes": []
    },
    "4452": {
        "notes": []
    },
    "2024": {
        "notes": [
            {
                "id": "6869ce6056dbd",
                "message": "✨✨✨",
                "created_at": 1751764576356,
                "viewers": [],
                "gradient": "linear-gradient(90deg, #ff8c42 0%, #ff3c3c 100%)",
                "actions": [],
                "reactions": []
            }
        ]
    },
    "2383": {
        "notes": []
    },
    "1911": {
        "notes": []
    },
    "2035": {
        "notes": []
    },
    "1918": {
        "notes": []
    },
    "2381": {
        "notes": []
    },
    "1926": {
        "notes": []
    },
    "2382": {
        "notes": []
    },
    "4454": {
        "notes": []
    },
    "4451": {
        "notes": []
    },
    "4455": {
        "notes": []
    }
}